LICENSE
pgn2json/__init__.py
pgn2json/computation/__init__.py
pgn2json/computation/pgn_conversion.py
pgn2json/config/__init__.py
pgn2json/config/constants.py
pgn2json/interface/__init__.py
pgn2json/interface/command_line.py
pgn2json/logs/__init__.py
pgn2json/logs/setup_logging.py
pgn2json/main.py
pgn2json/py.typed
pgn2json-0.1.2.dist-info/LICENSE
pgn2json-0.1.2.dist-info/METADATA
pgn2json-0.1.2.dist-info/WHEEL
pgn2json-0.1.2.dist-info/entry_points.txt
pgn2json-0.1.2.dist-info/RECORD
