Metadata-Version: 2.1
Name: pgn2json
Version: 0.1.2
Summary: Converts a PGN file to a JSON file. Designed for displaying Chess.com games inside of Obsidian using the Chess Study plugin.
Home-page: https://github.com/unkokaeru/pgn2json
License: MIT
Author: William Fayers
Author-email: william@fayers.com
Requires-Python: >=3.10,<4.0
Classifier: License :: OSI Approved :: MIT License
Classifier: Programming Language :: Python :: 3
Classifier: Programming Language :: Python :: 3.10
Classifier: Programming Language :: Python :: 3.11
Classifier: Programming Language :: Python :: 3.12
Requires-Dist: chess (>=1.11.0,<2.0.0)
Requires-Dist: rich (>=13.7.1,<14.0.0)
Requires-Dist: shortuuid (>=1.0.13,<2.0.0)
Project-URL: Repository, https://github.com/unkokaeru/pgn2json
